wfslib/__init__.py
wfslib/_wfs.py
wfslib/geometry.py
wfslib/setup.py
wfslib/shift_detector.c
wfslib/shift_detector.pyx
wfslib/shift_detector_numba.py
wfslib/subpert_generator.py
wfslib/wfs.py
wfslib-0.1.200.dist-info/entry_points.txt
wfslib-0.1.200.dist-info/WHEEL
wfslib-0.1.200.dist-info/METADATA
wfslib-0.1.200.dist-info/RECORD
