Metadata-Version: 2.1
Name: wfslib
Version: 0.1.200
Summary: Programming module for wave front data processing
License: MIT
Author: Zoya
Requires-Python: >=3.6,<4.0
Classifier: License :: OSI Approved :: MIT License
Classifier: Programming Language :: Python :: 3
Classifier: Programming Language :: Python :: 3.6
Classifier: Programming Language :: Python :: 3.7
Classifier: Programming Language :: Python :: 3.8
